elasticsearch_service/__init__.py
elasticsearch_service/elasticsearch_service.py
elasticsearch_service-0.23.dist-info/METADATA
elasticsearch_service-0.23.dist-info/WHEEL
elasticsearch_service-0.23.dist-info/top_level.txt
elasticsearch_service-0.23.dist-info/RECORD
