Metadata-Version: 2.1
Name: elasticsearch-service
Version: 0.23
Summary: easy access to elastic based on elasticsearch-dsl
Home-page: https://github.com/bertrandchevrier/elasticsearch-service.git
Author: The data handyman team
Author-email: chevrierbertrand@yahoo.fr
License: MIT
Platform: UNKNOWN
Classifier: Development Status :: 3 - Alpha
Requires-Python: >=3.6
Requires-Dist: elasticsearch
Requires-Dist: elasticsearch-dsl
Requires-Dist: pandas
